<?xml version="1.0" encoding="UTF-8"?>
<seiscomp xmlns="http://geofon.gfz-potsdam.de/ns/seiscomp3-schema/0.11" version="0.11"><Inventory><sensor publicID="Sensor/20220129132424.40513.8" name="BP.N14.BHE.2020.001.00.00.00" response="ResponsePAZ/20220129132424.405195.9"><description>Generic Velocity Sensor, Unity Gain-Generic Datalo</description><model>Velocity</model><manufacturer>Generic</manufacturer><unit>M/S</unit><remark>{"unit":"Velocity in Meters Per Second"}</remark></sensor><sensor publicID="Sensor/20220129132424.405567.13" name="BP.N14.BHN.2020.001.00.00.00" response="ResponsePAZ/20220129132424.405594.14"><description>Generic Velocity Sensor, Unity Gain-Generic Datalo</description><model>Velocity</model><manufacturer>Generic</manufacturer><unit>M/S</unit><remark>{"unit":"Velocity in Meters Per Second"}</remark></sensor><sensor publicID="Sensor/20220129132424.405863.18" name="BP.N14.BHZ.2020.001.00.00.00" response="ResponsePAZ/20220129132424.405887.19"><description>Generic Velocity Sensor, Unity Gain-Generic Datalo</description><model>Velocity</model><manufacturer>Generic</manufacturer><unit>M/S</unit><remark>{"unit":"Velocity in Meters Per Second"}</remark></sensor><datalogger publicID="Datalogger/20220129132424.404861.6" name="BP.N14.BHE.2020.001.00.00.00"><gain>1</gain><maxClockDrift>0</maxClockDrift><decimation sampleRateNumerator="100" sampleRateDenominator="1"><analogueFilterChain>ResponsePAZ/20220129132424.404982.7</analogueFilterChain></decimation></datalogger><datalogger publicID="Datalogger/20220129132424.405447.11" name="BP.N14.BHN.2020.001.00.00.00"><gain>1</gain><maxClockDrift>0</maxClockDrift><decimation sampleRateNumerator="100" sampleRateDenominator="1"><analogueFilterChain>ResponsePAZ/20220129132424.405525.12</analogueFilterChain></decimation></datalogger><datalogger publicID="Datalogger/20220129132424.405778.16" name="BP.N14.BHZ.2020.001.00.00.00"><gain>1</gain><maxClockDrift>0</maxClockDrift><decimation sampleRateNumerator="100" sampleRateDenominator="1"><analogueFilterChain>ResponsePAZ/20220129132424.405822.17</analogueFilterChain></decimation></datalogger><responsePAZ publicID="ResponsePAZ/20220129132424.404982.7" name="BP.N14..BHE.2020.001.00.00.00.stage_2"><type>A</type><gain>822410</gain><gainFrequency>1</gainFrequency><normalizationFactor>1</normalizationFactor><normalizationFrequency>1</normalizationFrequency><numberOfZeros>0</numberOfZeros><numberOfPoles>0</numberOfPoles></responsePAZ><responsePAZ publicID="ResponsePAZ/20220129132424.405195.9" name="BP.N14.BHE.2020.001.00.00.00"><type>A</type><gain>1000</gain><gainFrequency>1</gainFrequency><normalizationFactor>1</normalizationFactor><normalizationFrequency>1</normalizationFrequency><numberOfZeros>3</numberOfZeros><numberOfPoles>3</numberOfPoles><zeros>(0,0) (0,0) (0,0)</zeros><poles>(-0.22,0.235) (-0.22,-0.235) (-0.23,0)</poles></responsePAZ><responsePAZ publicID="ResponsePAZ/20220129132424.405525.12" name="BP.N14..BHN.2020.001.00.00.00.stage_2"><type>A</type><gain>822410</gain><gainFrequency>1</gainFrequency><normalizationFactor>1</normalizationFactor><normalizationFrequency>1</normalizationFrequency><numberOfZeros>0</numberOfZeros><numberOfPoles>0</numberOfPoles></responsePAZ><responsePAZ publicID="ResponsePAZ/20220129132424.405594.14" name="BP.N14.BHN.2020.001.00.00.00"><type>A</type><gain>1000</gain><gainFrequency>1</gainFrequency><normalizationFactor>1</normalizationFactor><normalizationFrequency>1</normalizationFrequency><numberOfZeros>3</numberOfZeros><numberOfPoles>3</numberOfPoles><zeros>(0,0) (0,0) (0,0)</zeros><poles>(-0.22,0.235) (-0.22,-0.235) (-0.23,0)</poles></responsePAZ><responsePAZ publicID="ResponsePAZ/20220129132424.405822.17" name="BP.N14..BHZ.2020.001.00.00.00.stage_2"><type>A</type><gain>822410</gain><gainFrequency>1</gainFrequency><normalizationFactor>1</normalizationFactor><normalizationFrequency>1</normalizationFrequency><numberOfZeros>0</numberOfZeros><numberOfPoles>0</numberOfPoles></responsePAZ><responsePAZ publicID="ResponsePAZ/20220129132424.405887.19" name="BP.N14.BHZ.2020.001.00.00.00"><type>A</type><gain>1000</gain><gainFrequency>1</gainFrequency><normalizationFactor>1</normalizationFactor><normalizationFrequency>1</normalizationFrequency><numberOfZeros>3</numberOfZeros><numberOfPoles>3</numberOfPoles><zeros>(0,0) (0,0) (0,0)</zeros><poles>(-0.22,0.235) (-0.22,-0.235) (-0.23,0)</poles></responsePAZ><network publicID="Network/20220129132424.404409.2" code="BP"><start>1980-01-01T00:00:00.0000Z</start><description>ABCD</description><netClass>p</netClass><archive>BI</archive><restricted>false</restricted><shared>true</shared><station publicID="Station/20220129132424.404517.3" code="N14"><start>2020-01-01T00:00:00.0000Z</start><description>N14</description><latitude>28.919</latitude><longitude>50.836</longitude><elevation>30</elevation><place>N14</place><affiliation>ABCD</affiliation><archive>BI</archive><restricted>false</restricted><shared>true</shared><sensorLocation publicID="SensorLocation/20220129132424.404676.4" code=""><start>2020-01-01T00:00:00.0000Z</start><latitude>28.919</latitude><longitude>50.836</longitude><elevation>30</elevation><stream publicID="Stream/20220129132424.404741.5" code="BHE" datalogger="Datalogger/20220129132424.404861.6" sensor="Sensor/20220129132424.40513.8"><start>2020-01-01T00:00:00.0000Z</start><dataloggerSerialNumber>xxxx</dataloggerSerialNumber><dataloggerChannel>2</dataloggerChannel><sensorSerialNumber>yyyy</sensorSerialNumber><sensorChannel>2</sensorChannel><sampleRateNumerator>100</sampleRateNumerator><sampleRateDenominator>1</sampleRateDenominator><depth>0</depth><azimuth>90</azimuth><dip>0</dip><gain>822410000</gain><gainFrequency>1</gainFrequency><gainUnit>M/S</gainUnit><format>Steim2</format><flags>CG</flags><restricted>false</restricted><shared>true</shared></stream><stream publicID="Stream/20220129132424.40537.10" code="BHN" datalogger="Datalogger/20220129132424.405447.11" sensor="Sensor/20220129132424.405567.13"><start>2020-01-01T00:00:00.0000Z</start><dataloggerSerialNumber>xxxx</dataloggerSerialNumber><dataloggerChannel>1</dataloggerChannel><sensorSerialNumber>yyyy</sensorSerialNumber><sensorChannel>1</sensorChannel><sampleRateNumerator>100</sampleRateNumerator><sampleRateDenominator>1</sampleRateDenominator><depth>0</depth><azimuth>0</azimuth><dip>0</dip><gain>822410000</gain><gainFrequency>1</gainFrequency><gainUnit>M/S</gainUnit><format>Steim2</format><flags>CG</flags><restricted>false</restricted><shared>true</shared></stream><stream publicID="Stream/20220129132424.405712.15" code="BHZ" datalogger="Datalogger/20220129132424.405778.16" sensor="Sensor/20220129132424.405863.18"><start>2020-01-01T00:00:00.0000Z</start><dataloggerSerialNumber>xxxx</dataloggerSerialNumber><dataloggerChannel>0</dataloggerChannel><sensorSerialNumber>yyyy</sensorSerialNumber><sensorChannel>0</sensorChannel><sampleRateNumerator>100</sampleRateNumerator><sampleRateDenominator>1</sampleRateDenominator><depth>0</depth><azimuth>0</azimuth><dip>-90</dip><gain>822410000</gain><gainFrequency>1</gainFrequency><gainUnit>M/S</gainUnit><format>Steim2</format><flags>CG</flags><restricted>false</restricted><shared>true</shared></stream></sensorLocation></station></network></Inventory></seiscomp>
